<Signature xmlns="http://www.w3.org/2000/09/xmldsig#" Id="AuthorSignature">
<SignedInfo>
<CanonicalizationMethod Algorithm="http://www.w3.org/2001/10/xml-exc-c14n#"></CanonicalizationMethod>
<SignatureMethod Algorithm="http://www.w3.org/2001/04/xmldsig-more#rsa-sha512"></SignatureMethod>
<Reference URI=".DS_Store">
<DigestMethod Algorithm="http://www.w3.org/2001/04/xmlenc#sha512"></DigestMethod>
<DigestValue>PvtIGkEvznYDoBtCLmP+v5IOuJi0Sb+UnqqcBiJvf6MgE11NrPJUDmAAr7TomZ7qd1qtTAplfTkQ
ku06OG4qsA==</DigestValue>
</Reference>
<Reference URI="AUTHORS">
<DigestMethod Algorithm="http://www.w3.org/2001/04/xmlenc#sha512"></DigestMethod>
<DigestValue>quFVIY21+TBnE0PlPc6dDwllRvMOIO+L6iNmr2NHBVfpAQk3xN23OGwHV5vcLJzxOfZ9C+32/g06
+sBjb2hYOw==</DigestValue>
</Reference>
<Reference URI="LICENSE.Flora">
<DigestMethod Algorithm="http://www.w3.org/2001/04/xmlenc#sha512"></DigestMethod>
<DigestValue>eMZs49Zoyv8pka7rh1hDfAR9c0J1Mc3Go+Yd/8y3382XiW4+49kRz7KJzjH959FGl3xkQZDNDYWt
3juskmdDvg==</DigestValue>
</Reference>
<Reference URI="NOTICE">
<DigestMethod Algorithm="http://www.w3.org/2001/04/xmlenc#sha512"></DigestMethod>
<DigestValue>6R2XTNsDCKoqH5wUr+gWDc4Fk6sDBYTdubXgZ/fXy6GFuHpRM/cewjZBdvYckJd47pCsTFMgpRX1
UOFkMrvkjg==</DigestValue>
</Reference>
<Reference URI="config.xml">
<DigestMethod Algorithm="http://www.w3.org/2001/04/xmlenc#sha512"></DigestMethod>
<DigestValue>Hl3jMA19pddsgdyNiOKdCl4LDrV7mmbWW4TjOMXwDQxthTqhRtXWZMLBraHu4KiFcDR/q+tNRIlj
aUT34sOLxg==</DigestValue>
</Reference>
<Reference URI="css%2Fassets%2FLKEuropaGroteskCity-Bold.woff">
<DigestMethod Algorithm="http://www.w3.org/2001/04/xmlenc#sha512"></DigestMethod>
<DigestValue>+64FmS7LXeqtu37xksmy4O7esJbwnAQ51cZxYRf2Bd+lTSHJ5uT1As0UogkIYUhNQ75M3b9o/ajN
ANnWf7eVSg==</DigestValue>
</Reference>
<Reference URI="css%2Fassets%2FLKEuropaGroteskCity-Bold.woff2">
<DigestMethod Algorithm="http://www.w3.org/2001/04/xmlenc#sha512"></DigestMethod>
<DigestValue>Vkf0iFsWCLsVM5oZ/7KpHbLQki1Ym3czC9/3+5NszvjY4fEuecEvMEFLdq8Cp1ZveAAVtdT1K4uO
vO3gL4tj3A==</DigestValue>
</Reference>
<Reference URI="css%2Fassets%2FLKEuropaGroteskCity-Medium.woff">
<DigestMethod Algorithm="http://www.w3.org/2001/04/xmlenc#sha512"></DigestMethod>
<DigestValue>IxzGUl2MtjUDIX9s4Tu7ZT8MbD3LTQPxpSYzNEN2AJ6DwqNEne8vKjQqH+ABOdNQDP2Bbz/mBV/v
wxZCoYe33g==</DigestValue>
</Reference>
<Reference URI="css%2Fassets%2FLKEuropaGroteskCity-Medium.woff2">
<DigestMethod Algorithm="http://www.w3.org/2001/04/xmlenc#sha512"></DigestMethod>
<DigestValue>px0bScSLERAjFZiOVzqT5Wooji5O6rgzqL8YdO4z4LjMvIDoTznkQK0A2dmrH+LKmjmLCEFQZQON
JH3em+WpGQ==</DigestValue>
</Reference>
<Reference URI="css%2Fassets%2FTheinhardt-Black.woff">
<DigestMethod Algorithm="http://www.w3.org/2001/04/xmlenc#sha512"></DigestMethod>
<DigestValue>IfwTsEK+R3G6T8VvD83BqNdH8HJI9UZqZ9sXbyIiVj+GRtPJzt3/NxrOHicYLssLYAPFm9hy2doR
zso6WfSiWg==</DigestValue>
</Reference>
<Reference URI="css%2Fassets%2FTheinhardt-Black.woff2">
<DigestMethod Algorithm="http://www.w3.org/2001/04/xmlenc#sha512"></DigestMethod>
<DigestValue>kjLjUcFT7dkMC58/4+Af/WoLaykPsbJFo/zCZteYpHPhkROUGPj56F+qf8TplKZfhGPu5tH1ggSc
2Xe8xE+ovg==</DigestValue>
</Reference>
<Reference URI="css%2Fassets%2FTheinhardt-Bold.woff">
<DigestMethod Algorithm="http://www.w3.org/2001/04/xmlenc#sha512"></DigestMethod>
<DigestValue>1cCHK9WYDcrp8ikVQhEzvC6WTPxEqpIkmBv7z9ShR9QjE1arQJ1N/0Gz6hFH5OcSJkw6BAWtkDVi
UADYMHnF6A==</DigestValue>
</Reference>
<Reference URI="css%2Fassets%2FTheinhardt-Bold.woff2">
<DigestMethod Algorithm="http://www.w3.org/2001/04/xmlenc#sha512"></DigestMethod>
<DigestValue>ain+1KWbEuZlohygI/TmubLaxWFrLFicWkZMK+RWf2zddUt9YVAITtzEbmtZAWbXZW7pFiwmDUxr
q8O133gOsQ==</DigestValue>
</Reference>
<Reference URI="css%2Fassets%2FTheinhardt-Light.woff">
<DigestMethod Algorithm="http://www.w3.org/2001/04/xmlenc#sha512"></DigestMethod>
<DigestValue>TRhzb8dO0KX7oXR8POJKcrBr4SEfZeMa1jxiUR0z5gi2Um2TkRO6daw6XIek/BIK8lJBZZ8tl6z9
h6Wewv5aqQ==</DigestValue>
</Reference>
<Reference URI="css%2Fassets%2FTheinhardt-Light.woff2">
<DigestMethod Algorithm="http://www.w3.org/2001/04/xmlenc#sha512"></DigestMethod>
<DigestValue>vRsluY466k7hAJYNG+8MkIPAZP7RLWTfZF6ntngPaYYYFxZs/KvLeLkrq7VAF2iaHFcFUB5E/YHp
JyWpajul7Q==</DigestValue>
</Reference>
<Reference URI="css%2Fassets%2FTheinhardt-Medium.woff">
<DigestMethod Algorithm="http://www.w3.org/2001/04/xmlenc#sha512"></DigestMethod>
<DigestValue>rCfm7NESo7++7mEfE3h7649F+3/lzU8SefRftGkv6B7HGmtzJ1+hHZ6Gm/lXB/KS8eNAnrV6Lidw
XwnyLjv13w==</DigestValue>
</Reference>
<Reference URI="css%2Fassets%2FTheinhardt-Medium.woff2">
<DigestMethod Algorithm="http://www.w3.org/2001/04/xmlenc#sha512"></DigestMethod>
<DigestValue>QAyvx1mjN0VU5XqzC59Jfq6qik7IYHkeVYFNrwRmrWoJZQkEvNlg4WGqg7AUsTFPpZVherSWpqZV
F1qqPLQ7KQ==</DigestValue>
</Reference>
<Reference URI="css%2Fassets%2FTheinhardt-Regular.woff">
<DigestMethod Algorithm="http://www.w3.org/2001/04/xmlenc#sha512"></DigestMethod>
<DigestValue>UHcBAB0IW0v6e4FDxGBx4S7GQ/ZdkAeyq/rnsxqd0xpOQyGgenh2UC8LDjAjgJwZqHewZ9bCpaFa
EA5JKpKDeg==</DigestValue>
</Reference>
<Reference URI="css%2Fassets%2FTheinhardt-Regular.woff2">
<DigestMethod Algorithm="http://www.w3.org/2001/04/xmlenc#sha512"></DigestMethod>
<DigestValue>R12TfFiOxC0NWek3lqhJOSuKAkxP7MUGcwcZPqTE/j3GT/YyQNUQiO+FnsGlqOo+OGtsZr+24+EW
R3DX19hW/w==</DigestValue>
</Reference>
<Reference URI="css%2Fassets%2Ftransfonter.org-20200910-091905%2Fdemo.html">
<DigestMethod Algorithm="http://www.w3.org/2001/04/xmlenc#sha512"></DigestMethod>
<DigestValue>YjzpYFU3vvVRgFGJ+WExJf7XqCMQT5427U2qG0MI6oN7KCG6rrRcGEdwr4qPukBfhZw1vHvXhGEe
jqaW2iEdUA==</DigestValue>
</Reference>
<Reference URI="css%2Fassets%2Ftransfonter.org-20200910-091905%2Fstylesheet.css">
<DigestMethod Algorithm="http://www.w3.org/2001/04/xmlenc#sha512"></DigestMethod>
<DigestValue>J6uuZrdHnjud1zg05ViyCCINBh/Lzb2bM4bVXbe2+KULYNdOHNCZfDf7Kio/nORMmOQe90hGGUUr
V9Jgh/47gw==</DigestValue>
</Reference>
<Reference URI="css%2Fstyle.css">
<DigestMethod Algorithm="http://www.w3.org/2001/04/xmlenc#sha512"></DigestMethod>
<DigestValue>NIRSVXjBpk8Vjq+J5+JYt3b91B+fJpYjY5AZtNSBnPbsj67OWZ4ZTr6qYjbJuUvC6S387khGyi3g
QkAu2yGqLg==</DigestValue>
</Reference>
<Reference URI="fallback_video%2F200910%20fallback.aep">
<DigestMethod Algorithm="http://www.w3.org/2001/04/xmlenc#sha512"></DigestMethod>
<DigestValue>0dEBhzFW+WgsyqUadqx5JjIpEwA/yRIWUVFChocJh3KWBM21eGV29GYVBoS0by4VdmfXw9ptGKb8
3QXCqkVVSw==</DigestValue>
</Reference>
<Reference URI="fallback_video%2F200910%20fallback_AME%2FtmpAEtoAMEProject-Komp%201.aep">
<DigestMethod Algorithm="http://www.w3.org/2001/04/xmlenc#sha512"></DigestMethod>
<DigestValue>0dEBhzFW+WgsyqUadqx5JjIpEwA/yRIWUVFChocJh3KWBM21eGV29GYVBoS0by4VdmfXw9ptGKb8
3QXCqkVVSw==</DigestValue>
</Reference>
<Reference URI="fallback_video%2Fdachmarke.psd">
<DigestMethod Algorithm="http://www.w3.org/2001/04/xmlenc#sha512"></DigestMethod>
<DigestValue>UA5haNu8ENCidor9bku6n5e7QTsOKFTzmFIo6PbpycuLPVyCWebvo1PNmmeuy/T7AHlc4nlz1ugF
ng35hGv+Ng==</DigestValue>
</Reference>
<Reference URI="icon.png">
<DigestMethod Algorithm="http://www.w3.org/2001/04/xmlenc#sha512"></DigestMethod>
<DigestValue>fXoATqyI+nmtLRYRn0oyENyN5GgPo8v0eNcMQOpSKuiw7cT8D/Z25m6leHYLUcQH6v1M79/igY3h
R7UqDNL+wg==</DigestValue>
</Reference>
<Reference URI="icon2.png">
<DigestMethod Algorithm="http://www.w3.org/2001/04/xmlenc#sha512"></DigestMethod>
<DigestValue>946Jo6sS7/VGXjx+Jvt9we7GUgw+Sn2EmCZ5CGssd1FA2MzJIABHVH4FUShkCHQ1lbLg43TZ2kUe
xXbY9fX1EQ==</DigestValue>
</Reference>
<Reference URI="index.html">
<DigestMethod Algorithm="http://www.w3.org/2001/04/xmlenc#sha512"></DigestMethod>
<DigestValue>Bf9PAqQsalVX8ivHvBrITEvtzkJ20wex5xBqF67yS+h63VOy4n4uy13r15vi4XLWGg8WxRVHghsG
6B6+sQeQ2g==</DigestValue>
</Reference>
<Reference URI="js%2Ftge.file_handling.js">
<DigestMethod Algorithm="http://www.w3.org/2001/04/xmlenc#sha512"></DigestMethod>
<DigestValue>ZrBFOzc86XSsDll2bsshXZSCB1z7Q3obLh4+ItEsz5bvJv1FM89MmhpJwNjAjvU1mqhU/UY0JWDe
x/Bdows17w==</DigestValue>
</Reference>
<Reference URI="js%2Ftge.main.js">
<DigestMethod Algorithm="http://www.w3.org/2001/04/xmlenc#sha512"></DigestMethod>
<DigestValue>yxZsjuwhvvpj5HowEloylFeyjM25KCep/zaNEu6tFw7oi0mdFN5QOTd+uFqUgvtib2WjzCUVKu/a
dhgw5QRY9Q==</DigestValue>
</Reference>
<Reference URI="js%2Ftge.server_communication.js">
<DigestMethod Algorithm="http://www.w3.org/2001/04/xmlenc#sha512"></DigestMethod>
<DigestValue>z4PhNX7vuL3xVChQ1m2AB9Yg5AULVxXcg/SpIdNs6c5H0NE8XYXysP+DGNKHfuwvY7kxvUdBeoGl
ODJ6+SfaPg==</DigestValue>
</Reference>
<Reference URI="js%2Ftge.state_machine.js">
<DigestMethod Algorithm="http://www.w3.org/2001/04/xmlenc#sha512"></DigestMethod>
<DigestValue>Jh3+PyzYqFfVEl1LdhTcoYwap2KT5YXUsHJ3xxmgJzH49IqBn/rb5d7XlSQNBj6607tV6OeIL2c7
oDtfRqjsCA==</DigestValue>
</Reference>
<Reference URI="js%2Ftge.variables.js">
<DigestMethod Algorithm="http://www.w3.org/2001/04/xmlenc#sha512"></DigestMethod>
<DigestValue>ADLOrjIwVaeyqChtle2tWuGwfLJzdkftfGiI9K6txEnpaTyEKIv8cYxb2rIMn9QaEtKzInyCs+08
0PKFGIZbkg==</DigestValue>
</Reference>
<Reference URI="js%2Ftge.video_handling.js">
<DigestMethod Algorithm="http://www.w3.org/2001/04/xmlenc#sha512"></DigestMethod>
<DigestValue>1x4wCk4YEvc0fMv9tG+qPcOjwgBUyYd7SmXvIgijc+iE4kmDk+WQ60xejyjg11+tYEP09u8zFt3+
f6j9qH+AFQ==</DigestValue>
</Reference>
<Reference URI="sssp_config.xml">
<DigestMethod Algorithm="http://www.w3.org/2001/04/xmlenc#sha512"></DigestMethod>
<DigestValue>Bx+pWu/2lsEKwWr2ckFJ9OGeoG4mbLBinZnMQq3v+HRlWqAcf+I8Xjjwpujlv9eGkzb3wUa381fo
WBF9LeTiRA==</DigestValue>
</Reference>
<Reference URI="tge_app.wgt">
<DigestMethod Algorithm="http://www.w3.org/2001/04/xmlenc#sha512"></DigestMethod>
<DigestValue>Xr3m1ZM8aHB95qKkGLHsILTreeCvrz3G3CTImauSy15vyNMFmQDg3TPX2GhN/D9+GhTKBpY42/b1
EKN95I0d/A==</DigestValue>
</Reference>
<Reference URI="#prop">
<Transforms>
<Transform Algorithm="http://www.w3.org/2006/12/xml-c14n11"></Transform>
</Transforms>
<DigestMethod Algorithm="http://www.w3.org/2001/04/xmlenc#sha512"></DigestMethod>
<DigestValue>aXbSAVgmAz0GsBUeZ1UmNDRrxkWhDUVGb45dZcNRq429wX3X+x6kaXT3NdNDTSNVTU+ypkysPMGv
QY10fG1EWQ==</DigestValue>
</Reference>
</SignedInfo>
<SignatureValue>
brrUTD5eg/oA/byHwrSPHkFe7QYhNdkwN3qMgjPnYSWfCssaBKMB/h8qR61bAQA/KZ3DtLu+MgNH
V+56Q7gk2m/2dTAdk2x2uZbhqI3G/GF/to0UnwFNMXThcNjMoJxGuIdgiiJnTGF3+nN3lSBGIyRN
PM4zPibkN4ai9bFI78U=
</SignatureValue>
<KeyInfo>
<X509Data>
<X509Certificate>
MIICmTCCAYGgAwIBAgIGAXMzXU/cMA0GCSqGSIb3DQEBDQUAMFYxGjAYBgNVBAoMEVRpemVuIEFz
c29jaWF0aW9uMRowGAYDVQQLDBFUaXplbiBBc3NvY2lhdGlvbjEcMBoGA1UEAwwTVGl6ZW4gRGV2
ZWxvcGVycyBDQTAeFw0yMDA3MDkxMTM3MDBaFw0yNzAxMDEwMDAwMDBaMBUxEzARBgNVBAMMCmp1
bGlhbi50Z2UwgZ8wDQYJKoZIhvcNAQEBBQADgY0AMIGJAoGBAILe6WavI7b0aOk8VMQl66R+xzFU
lRZbKO7xB1jzv1h1CpcZtfZ7hrpNonmwLpbMrnDBJwkExzelRR+3VP5Dnvsd1jNR/VxK8FCepj9N
+f6ULeXoH//ngnt8E/PXxOAECyS/0IEorqrEwIzsGIwf3Q9JskTHZv5msV4Q+zXFrUMjAgMBAAGj
MjAwMAwGA1UdEwEB/wQCMAAwCwYDVR0PBAQDAgeAMBMGA1UdJQQMMAoGCCsGAQUFBwMDMA0GCSqG
SIb3DQEBDQUAA4IBAQCdoQc0nP7/rvNlcn7JdOanirP0hFXEuVXVDjuMCt+/pQLfU2iRASJ4fvjI
sNv0KMcTpt+MhzLcWX1rm1jn2b26tmx6DDWJR1/uTjb0ckgGstTkbTrYCL1GgTQ/59B08H3UxVrC
8WCdSsuyj8EXOv3cEmQVjHy7w8USvdo850QH/0MO84QotDFUKK2OXsCdEoyuFtv4xEctdXDyYeG3
idp8BbGSQsCCQqqqFTr+tc537rJHJoQubQLAQISRXP8GZ/xSDMYMnj3QnrCw952HpqIiMw0lBCHh
sKF6NqHxWt08S3soW5SCPYId2KB7g0QABol1ODEbEMVWXglqpJiBeXSf
</X509Certificate>
<X509Certificate>
MIIDOTCCAiGgAwIBAgIBATANBgkqhkiG9w0BAQUFADBYMRowGAYDVQQKDBFUaXplbiBBc3NvY2lh
dGlvbjEaMBgGA1UECwwRVGl6ZW4gQXNzb2NpYXRpb24xHjAcBgNVBAMMFVRpemVuIERldmVsb3Bl
cnMgUm9vdDAeFw0xMjAxMDEwMDAwMDBaFw0yNzAxMDEwMDAwMDBaMFYxGjAYBgNVBAoMEVRpemVu
IEFzc29jaWF0aW9uMRowGAYDVQQLDBFUaXplbiBBc3NvY2lhdGlvbjEcMBoGA1UEAwwTVGl6ZW4g
RGV2ZWxvcGVycyBDQTCCASIwDQYJKoZIhvcNAQEBBQADggEPADCCAQoCggEBANVGhRGmMIUyBA7o
PCz8Sxut6z6HNkF4oDIuzuKaMzRYPeWodwe9O0gmqAkToQHfwg2giRhE5GoPld0fq+OYMMwSasCu
g8dwODx1eDeSYVuOLWRxpAmbTXOsSFi6VoWeyaPEm18JBHvZBsU5YQtgZ6Kp7MqzvQg3pXOxtajj
vyHxiatJl+xXrHgcXC1wgyG3buty7u/Fi2mvKXJ0PRJcCjjK81dqe/Vr20sRUCrbk02zbm5ggFt/
jIEhV8wbFRQpliobc7J4dSTKhFfrqGM8rdd54LYhD7gSI1CFSe16pUXfcVR7FhJztRaiGLnCrwBE
dyTZ248+D4L/qR/D0axb3jcCAwEAAaMQMA4wDAYDVR0TBAUwAwEB/zANBgkqhkiG9w0BAQUFAAOC
AQEAnOXXQ/1O/QTDHyrmQDtFziqPY3xWlJBqJtEqXiT7Y+Ljpe66e+Ee/OjQMlZe8gu21/8cKklH
95RxjopMWCVedXDUbWdvS2+CdyvVW/quT2E0tjqIzXDekUTYwwhlPWlGxvfj3VsxqSFq3p8Brl04
1Gx5RKAGyKVsMfTLhbbwSWwApuBUxYfcNpKwLWGPXkysu+HctY03OKv4/xKBnVWiN8ex/Sgesi0M
+OBAOMdZMPK32uJBTeKFx1xZgTLIhk45V0hPOomPjZloiv0LSS11eyd451ufjW0iHRE7WlpR6EvI
W6TFyZgMpQq+kg4hWl2SBTf3s2VI8Ygz7gj8TMlClg==
</X509Certificate>
</X509Data>
</KeyInfo>
<Object Id="prop"><SignatureProperties xmlns:dsp="http://www.w3.org/2009/xmldsig-properties"><SignatureProperty Id="profile" Target="#AuthorSignature"><dsp:Profile URI="http://www.w3.org/ns/widgets-digsig#profile"></dsp:Profile></SignatureProperty><SignatureProperty Id="role" Target="#AuthorSignature"><dsp:Role URI="http://www.w3.org/ns/widgets-digsig#role-author"></dsp:Role></SignatureProperty><SignatureProperty Id="identifier" Target="#AuthorSignature"><dsp:Identifier></dsp:Identifier></SignatureProperty></SignatureProperties></Object>
</Signature>